HISTORY.rst
MANIFEST.in
README.rst
setup.py
lib/nelsnmp/__init__.py
lib/nelsnmp/cisco_oids.py
lib/nelsnmp/errors.py
lib/nelsnmp/snmp.py
lib/nelsnmp.egg-info/PKG-INFO
lib/nelsnmp.egg-info/SOURCES.txt
lib/nelsnmp.egg-info/dependency_links.txt
lib/nelsnmp.egg-info/requires.txt
lib/nelsnmp.egg-info/top_level.txt
lib/nelsnmp/hostinfo/__init__.py
lib/nelsnmp/hostinfo/collect.py
lib/nelsnmp/hostinfo/device.py
lib/nelsnmp/hostinfo/version.py
lib/nelsnmp/oids/__init__.py
lib/nelsnmp/vendors/__init__.py
lib/nelsnmp/vendors/mappings.py
lib/nelsnmp/vendors/airespace/__init__.py
lib/nelsnmp/vendors/airespace/oids.py
lib/nelsnmp/vendors/alcatel/__init__.py
lib/nelsnmp/vendors/alcatel/versions.py
lib/nelsnmp/vendors/arista/__init__.py
lib/nelsnmp/vendors/arista/versions.py
lib/nelsnmp/vendors/cisco/__init__.py
lib/nelsnmp/vendors/cisco/cdp.py
lib/nelsnmp/vendors/cisco/oids.py
lib/nelsnmp/vendors/cisco/versions.py
lib/nelsnmp/vendors/ericsson/__init__.py
lib/nelsnmp/vendors/ericsson/versions.py
lib/nelsnmp/vendors/extreme/__init__.py
lib/nelsnmp/vendors/extreme/versions.py
lib/nelsnmp/vendors/hpe/__init__.py
lib/nelsnmp/vendors/hpe/versions.py
lib/nelsnmp/vendors/huawei/__init__.py
lib/nelsnmp/vendors/huawei/versions.py
lib/nelsnmp/vendors/juniper/__init__.py
lib/nelsnmp/vendors/juniper/versions.py
lib/nelsnmp/vendors/metamako/__init__.py
lib/nelsnmp/vendors/metamako/versions.py
lib/nelsnmp/vendors/synology/__init__.py
lib/nelsnmp/vendors/synology/oids.py
lib/nelsnmp/vendors/synology/versions.py