Metadata-Version: 1.1
Name: nelsnmp
Version: 0.2.9
Summary: A wrapper module for pysnmp
Home-page: https://networklore.com/nelsnmp/
Author: Patrick Ogenstad
Author-email: patrick@ogenstad.com
License: Apache
Platform: UNKNOWN
Classifier: Development Status :: 4 - Beta
Classifier: Intended Audience :: Developers
Classifier: Intended Audience :: System Administrators
